{
  "source": "luxe.ResourceStats",
  "doc": "",
  "links": [],
  "toplinks": [],
  "sections": [
    {
      "name": "Members",
      "link": "#Members",
      "values": [
        {
          "name": "render_textures",
          "meta": [],
          "ispublic": true,
          "isinline": false,
          "isstatic": false,
          "signature": "render_textures : Int",
          "type": "Int",
          "doc": ""
        },
        {
          "name": "datas",
          "meta": [],
          "ispublic": true,
          "isinline": false,
          "isstatic": false,
          "signature": "datas : Int",
          "type": "Int",
          "doc": ""
        },
        {
          "name": "sounds",
          "meta": [],
          "ispublic": true,
          "isinline": false,
          "isstatic": false,
          "signature": "sounds : Int",
          "type": "Int",
          "doc": ""
        },
        {
          "name": "texts",
          "meta": [],
          "ispublic": true,
          "isinline": false,
          "isstatic": false,
          "signature": "texts : Int",
          "type": "Int",
          "doc": ""
        },
        {
          "name": "unknown",
          "meta": [],
          "ispublic": true,
          "isinline": false,
          "isstatic": false,
          "signature": "unknown : Int",
          "type": "Int",
          "doc": ""
        },
        {
          "name": "textures",
          "meta": [],
          "ispublic": true,
          "isinline": false,
          "isstatic": false,
          "signature": "textures : Int",
          "type": "Int",
          "doc": ""
        },
        {
          "name": "shaders",
          "meta": [],
          "ispublic": true,
          "isinline": false,
          "isstatic": false,
          "signature": "shaders : Int",
          "type": "Int",
          "doc": ""
        },
        {
          "name": "resources",
          "meta": [],
          "ispublic": true,
          "isinline": false,
          "isstatic": false,
          "signature": "resources : Int",
          "type": "Int",
          "doc": ""
        },
        {
          "name": "fonts",
          "meta": [],
          "ispublic": true,
          "isinline": false,
          "isstatic": false,
          "signature": "fonts : Int",
          "type": "Int",
          "doc": ""
        }
      ]
    },
    {
      "name": "StaticMethods",
      "link": "#StaticMethods",
      "values": []
    },
    {
      "name": "Methods",
      "link": "#Methods",
      "values": [
        {
          "name": "reset",
          "meta": [],
          "ispublic": true,
          "isstatic": false,
          "isinline": false,
          "doc": "",
          "signature": "reset() : Void",
          "return": ": Void",
          "args": []
        },
        {
          "name": "new",
          "meta": [],
          "ispublic": true,
          "isstatic": false,
          "isinline": false,
          "doc": "",
          "signature": "new() ",
          "return": "",
          "args": []
        },
        {
          "name": "toString",
          "meta": [],
          "ispublic": true,
          "isstatic": false,
          "isinline": false,
          "doc": "",
          "signature": "toString() : String",
          "return": ": String",
          "args": []
        }
      ]
    }
  ]
}