{
  "source": "luxe.structural.BalancedBinarySearchTraverseMethod",
  "doc": "",
  "links": [],
  "toplinks": [],
  "sections": [
    {
      "name": "Values",
      "link": "#Values",
      "values": [
        {
          "name": "PreOrder",
          "signature": "luxe.structural.BalancedBinarySearchTraverseMethod.PreOrder",
          "doc": ""
        },
        {
          "name": "InOrder",
          "signature": "luxe.structural.BalancedBinarySearchTraverseMethod.InOrder",
          "doc": ""
        },
        {
          "name": "PostOrder",
          "signature": "luxe.structural.BalancedBinarySearchTraverseMethod.PostOrder",
          "doc": ""
        }
      ]
    },
    {
      "name": "Meta",
      "link": "#Meta",
      "values": [
        {
          "name": ":flatEnum",
          "value": ""
        }
      ]
    }
  ]
}